pytest_tst.py
pytest_tst-0.1.3.dist-info/LICENSE
pytest_tst-0.1.3.dist-info/METADATA
pytest_tst-0.1.3.dist-info/WHEEL
pytest_tst-0.1.3.dist-info/entry_points.txt
pytest_tst-0.1.3.dist-info/top_level.txt
pytest_tst-0.1.3.dist-info/RECORD
