Metadata-Version: 2.1
Name: pytest-tst
Version: 0.1.3
Summary: Customize pytest options, output and exit code to make it compatible with tst
Home-page: https://github.com/daltonserey/pytest-tst
Author: Dalton Serey
Author-email: daltonserey@gmail.com
Maintainer: Dalton Serey
Maintainer-email: daltonserey@gmail.com
License: MIT
Platform: UNKNOWN
Requires-Python: >3.6
License-File: LICENSE
Requires-Dist: pytest (>=5.0.0)
Requires-Dist: tst (>=0.15.1)
